jwt_client_authentication/__init__.py
jwt_client_authentication/authentication.py
jwt_client_authentication/settings.py
jwt_client_authentication-0.1.2b0.dist-info/METADATA
jwt_client_authentication-0.1.2b0.dist-info/WHEEL
jwt_client_authentication-0.1.2b0.dist-info/top_level.txt
jwt_client_authentication-0.1.2b0.dist-info/RECORD
